pyictacp/__init__.py
pyictacp/checksum.py
pyictacp/client.py
pyictacp/connection/__init__.py
pyictacp/connection/tcp.py
pyictacp/encryption.py
pyictacp/packet/__init__.py
pyictacp/packet/command.py
pyictacp/packet/data.py
pyictacp/packet/system.py
pyictacp/record/__init__.py
pyictacp/record/area.py
pyictacp/record/door.py
pyictacp/record/input.py
pyictacp/record/output.py
pyictacp/record/troubleinput.py
pyictacp/record/variable.py
pyictacp/typez.py
pyictacp/util.py
pyictacp-0.2.2.dist-info/WHEEL
pyictacp-0.2.2.dist-info/METADATA
pyictacp-0.2.2.dist-info/RECORD
